{
    "annotations": {
      "list": [
        {
          "builtIn": 1,
          "datasource": {
            "type": "grafana",
            "uid": "-- Grafana --"
          },
          "enable": true,
          "hide": true,
          "iconColor": "rgba(0, 211, 255, 1)",
          "name": "Annotations & Alerts",
          "type": "dashboard"
        }
      ]
    },
    "editable": true,
    "fiscalYearStartMonth": 0,
    "graphTooltip": 0,
    "id": 3,
    "links": [],
    "panels": [
      {
        "datasource": {
          "type": "prometheus",
          "uid": "b53bd1bd-00b1-413f-97be-6d2bea515633"
        },
        "fieldConfig": {
          "defaults": {
            "color": {
              "mode": "thresholds"
            },
            "fieldMinMax": false,
            "mappings": [],
            "thresholds": {
              "mode": "absolute",
              "steps": [
                {
                  "color": "green",
                  "value": null
                }
              ]
            },
            "unit": "s"
          },
          "overrides": []
        },
        "gridPos": {
          "h": 8,
          "w": 12,
          "x": 0,
          "y": 0
        },
        "id": 2,
        "options": {
          "colorMode": "value",
          "graphMode": "area",
          "justifyMode": "auto",
          "orientation": "auto",
          "percentChangeColorMode": "standard",
          "reduceOptions": {
            "calcs": [
              "lastNotNull"
            ],
            "fields": "",
            "values": false
          },
          "showPercentChange": false,
          "textMode": "auto",
          "wideLayout": true
        },
        "pluginVersion": "11.3.0",
        "targets": [
          {
            "disableTextWrap": false,
            "editorMode": "code",
            "expr": "time() - backup_last_success_time{user=\"1nnu\"}",
            "fullMetaSearch": false,
            "includeNullMetadata": true,
            "legendFormat": "{{service}}",
            "range": true,
            "refId": "A",
            "useBackend": false
          }
        ],
        "title": "Panel Title",
        "type": "stat"
      },
      {
        "datasource": {
          "type": "prometheus",
          "uid": "b53bd1bd-00b1-413f-97be-6d2bea515633"
        },
        "fieldConfig": {
          "defaults": {
            "color": {
              "mode": "thresholds"
            },
            "mappings": [],
            "thresholds": {
              "mode": "absolute",
              "steps": [
                {
                  "color": "green",
                  "value": null
                },
                {
                  "color": "red",
                  "value": 80
                }
              ]
            }
          },
          "overrides": []
        },
        "gridPos": {
          "h": 8,
          "w": 12,
          "x": 12,
          "y": 0
        },
        "id": 1,
        "options": {
          "colorMode": "value",
          "graphMode": "area",
          "justifyMode": "auto",
          "orientation": "auto",
          "percentChangeColorMode": "standard",
          "reduceOptions": {
            "calcs": [
              "lastNotNull"
            ],
            "fields": "",
            "values": false
          },
          "showPercentChange": false,
          "textMode": "auto",
          "wideLayout": true
        },
        "pluginVersion": "11.3.0",
        "targets": [
          {
            "datasource": {
              "type": "prometheus",
              "uid": "b53bd1bd-00b1-413f-97be-6d2bea515633"
            },
            "disableTextWrap": false,
            "editorMode": "builder",
            "exemplar": false,
            "expr": "backups_total{user=\"1nnu\"}",
            "format": "time_series",
            "fullMetaSearch": false,
            "includeNullMetadata": true,
            "instant": false,
            "interval": "",
            "legendFormat": "{{service}}{{type}}",
            "range": true,
            "refId": "A",
            "useBackend": false
          }
        ],
        "title": "Panel Title",
        "type": "stat"
      }
    ],
    "preload": false,
    "schemaVersion": 40,
    "tags": [],
    "templating": {
      "list": []
    },
    "time": {
      "from": "now-5m",
      "to": "now"
    },
    "timepicker": {},
    "timezone": "browser",
    "title": "backups",
    "uid": "de354kj0d6fb4e",
    "version": 4,
    "weekStart": ""
  }